[
  {
    "id": 1,
    "name": "Hangul g",
    "image": "../images/hangulg.PNG",
    "occupation": "Fry Cook",
    "location": "A Pineapple Under the Sea"
  },
  {
    "id": 2,
    "name": "Hangul a",
    "image": "../images/hangula.PNG",
    "occupation": "Restaurant Owner",
    "location": "A Giant Anchor"
  },
  {
    "id": 3,
    "name": "Hangul b",
    "image": "../images/hangulb.PNG",
    "occupation": "Cashier",
    "location": "An Easter Island Head"
  },
  {
    "id": 4,
    "name": "Hangul h",
    "image": "../images/hangulh.PNG",
    "occupation": "Boy Genius",
    "location": "A Secret Laboratory"
  },
  {
    "id": 5,
    "name": "Hangul j",
    "image": "../images/hangulj.PNG",
    "occupation": "A Cowardly Dog",
    "location": "Nowhere, Kansas"
  },
  {
    "id": 6,
    "name": "Hangul m",
    "image": "../images/hangulm.PNG",
    "occupation": "Student",
    "location": "Bluffington"
  },
  {
    "id": 7,
    "name": "Hangul n",
    "image": "../images/hanguln.PNG",
    "occupation": "Looney Toon",
    "location": "A Rabbit Burrow"
  },
  {
    "id": 8,
    "name": "Hangul r",
    "image": "../images/hangulr.PNG",
    "occupation": "Ladies Man",
    "location": "Aron City"
  },
  {
    "id": 9,
    "name": "Hangul s",
    "image": "../images/hanguls.PNG",
    "occupation": "Adventurer",
    "location": "California"
  },
  {
    "id": 10,
    "name": "Hangul t",
    "image": "../images/hangult.PNG",
    "occupation": "Cashier",
    "location": "O-Town, California"
  },
  {
    "id": 11,
    "name": "Hangul yu",
    "image": "../images/hangulyu.PNG",
    "occupation": "Superhero",
    "location": "Earth"
  },
  {
    "id": 12,
    "name": "Hangul d",
    "image": "../images/hanguld.PNG",
    "occupation": "Ahhhh! A Real Monster!",
    "location": "Under a City Dump"
  }
]
